MANIFEST.in
README.md
setup.py
dockerbuildtest/__init__.py
dockerbuildtest/__main__.py
dockerbuildtest.egg-info/PKG-INFO
dockerbuildtest.egg-info/SOURCES.txt
dockerbuildtest.egg-info/dependency_links.txt
dockerbuildtest.egg-info/not-zip-safe
dockerbuildtest.egg-info/requires.txt
dockerbuildtest.egg-info/top_level.txt
dockerbuildtest/appRoutes/__init__.py
dockerbuildtest/appRoutes/app_view_routes.py
dockerbuildtest/core/__init__.py
dockerbuildtest/core/docker_build_client.py
dockerbuildtest/core/utils/__init__.py
dockerbuildtest/core/utils/validateSchema.py
dockerbuildtest/handlers/__init__.py
dockerbuildtest/handlers/default_views.py
dockerbuildtest/handlers/docker_build_handler.py